MANIFEST.in
README
setup.py
doc/.DS_Store
doc/.buildinfo
doc/LICENSE
doc/.doctrees/base.doctree
doc/.doctrees/data.doctree
doc/.doctrees/environment.pickle
doc/.doctrees/index.doctree
doc/.doctrees/plot.doctree
doc/html/.buildinfo
doc/html/base.html
doc/html/confounders.html
doc/html/data.html
doc/html/genindex.html
doc/html/index.html
doc/html/objects.inv
doc/html/plot.html
doc/html/py-modindex.html
doc/html/results.html
doc/html/search.html
doc/html/searchindex.js
doc/html/timeshift.html
doc/html/tutorial.html
doc/html/usage.html
doc/html/.doctrees/base.doctree
doc/html/.doctrees/confounders.doctree
doc/html/.doctrees/data.doctree
doc/html/.doctrees/index.doctree
doc/html/.doctrees/plot.doctree
doc/html/.doctrees/results.doctree
doc/html/.doctrees/timeshift.doctree
doc/html/.doctrees/tutorial.doctree
doc/html/.doctrees/usage.doctree
doc/html/_images/plotGPTwoSampleDifferential.pdf
doc/html/_images/plotGPTwoSampleSame.pdf
doc/html/_images/timeshiftexample.pdf
doc/html/_images/math/17c8b807f742be9b271253d1e4be7a148914abbf.png
doc/html/_modules/index.html
doc/html/_modules/gptwosample/confounder/confounder.html
doc/html/_modules/gptwosample/data/dataIO.html
doc/html/_modules/gptwosample/data/data_base.html
doc/html/_modules/gptwosample/plot/plot_basic.html
doc/html/_modules/gptwosample/twosample/twosample.html
doc/html/_modules/gptwosample/twosample/twosample_base.html
doc/html/_sources/base.txt
doc/html/_sources/confounders.txt
doc/html/_sources/data.txt
doc/html/_sources/index.txt
doc/html/_sources/plot.txt
doc/html/_sources/results.txt
doc/html/_sources/timeshift.txt
doc/html/_sources/tutorial.txt
doc/html/_sources/usage.txt
doc/html/_static/ajax-loader.gif
doc/html/_static/basic.css
doc/html/_static/comment-bright.png
doc/html/_static/comment-close.png
doc/html/_static/comment.png
doc/html/_static/default.css
doc/html/_static/doctools.js
doc/html/_static/down-pressed.png
doc/html/_static/down.png
doc/html/_static/file.png
doc/html/_static/jquery.js
gptwosample.egg-info/PKG-INFO
gptwosample.egg-info/SOURCES.txt
gptwosample.egg-info/dependency_links.txt
gptwosample.egg-info/entry_points.txt
gptwosample.egg-info/requires.txt
gptwosample.egg-info/top_level.txt
