Metadata-Version: 1.1
Name: gptwosample
Version: 0.1.19
Summary: 
Home-page: https://www.assembla.com/code/gptwosample/git/nodes
Author: Max Zwießele, Oliver Stegle
Author-email: ibinbei@gmail.com
License: Apache License v2.0
Platform: UNKNOWN
Classifier: Development Status :: 4 - Beta
Classifier: Environment :: Console
Classifier: Intended Audience :: End Users/Desktop
Classifier: Intended Audience :: Developers
Classifier: License :: OSI Approved :: Apache Software License
Classifier: Operating System :: MacOS :: MacOS X
Classifier: Operating System :: Microsoft :: Windows
Classifier: Operating System :: POSIX
Classifier: Programming Language :: Python
Classifier: Topic :: Scientific/Engineering
Classifier: Topic :: Scientific/Engineering :: Information Analysis
Classifier: Topic :: Scientific/Engineering :: Visualization
Classifier: Topic :: Software Development :: Libraries
Requires: numpy
Requires: scipy
Requires: pygp
Requires: matplotlib
